coraline/__init__.py
coraline/config.py
coraline/exceptions.py
coraline/field.py
coraline/model.py
coraline/types.py
coraline-1.3.0.dist-info/LICENSE
coraline-1.3.0.dist-info/METADATA
coraline-1.3.0.dist-info/WHEEL
coraline-1.3.0.dist-info/RECORD
