Metadata-Version: 2.3
Name: coraline
Version: 1.3.0
Summary: Use Pydantic Models to handle AWS DynamoDB tables
License: MIT
Author: Chris Maillefaud
Author-email: chrismaille@users.noreply.github.com
Requires-Python: >=3.11,<4
Classifier: License :: OSI Approved :: MIT License
Classifier: Programming Language :: Python :: 3
Classifier: Programming Language :: Python :: 3.11
Classifier: Programming Language :: Python :: 3.12
Classifier: Programming Language :: Python :: 3.13
Provides-Extra: boto
Requires-Dist: asbool
Requires-Dist: boto3 ; extra == "boto"
Requires-Dist: inflection
Requires-Dist: loguru
Requires-Dist: py-lamina
Requires-Dist: pydantic
Requires-Dist: stela
